<?xml version='1.0' encoding='utf-8'?>
<mods:mods xmlns:mods="http://www.loc.gov/mods/v3" xmlns:xsi="http://www.w3.org/2001/XMLSchema-instance" xsi:schemaLocation="http://www.loc.gov/mods/v3 http://www.loc.gov/standards/mods/v3/mods-3-7.xsd">
   <mods:titleInfo>
      <mods:title>BLM - Colorado Oil Shale Leases</mods:title>
   </mods:titleInfo>
   <mods:typeOfResource>Dataset</mods:typeOfResource>
   <mods:originInfo>
      <mods:dateIssued encoding="w3cdtf">2018-09-20</mods:dateIssued>
      <mods:publisher>U.S. Department of the Interior, Bureau of Land Management (BLM)</mods:publisher>
   </mods:originInfo>
   <mods:language>
      <mods:languageTerm type="text">English</mods:languageTerm>
   </mods:language>
   <mods:subject valueURI="http://id.worldcat.org/fast/fst01115131">
      <mods:topic>Shale</mods:topic>
   </mods:subject>
   <mods:subject valueURI="http://id.worldcat.org/fast/fst01059260">
      <mods:topic>Petroleum</mods:topic>
   </mods:subject>
   <mods:subject valueURI="http://id.worldcat.org/fast/fst01022445">
      <mods:topic>Minerals</mods:topic>
   </mods:subject>
   <mods:subject>
      <mods:cartographics>
         <mods:coordinates>W108.45121831058042,W108.33438384575201,N39.92815915702802,N39.852189670766954</mods:coordinates>
      </mods:cartographics>
   </mods:subject>
   <mods:subject>
      <mods:geographic>United States</mods:geographic>
   </mods:subject>
   <mods:name type="corporate">
      <mods:namePart>U.S. Department of the Interior, Bureau of Land Management (BLM)</mods:namePart>
      <mods:role>
         <mods:roleTerm type="text">creator</mods:roleTerm>
      </mods:role>
   </mods:name>
   <mods:physicalDescription>
      <mods:form authority="LCGFT" authorityURI="http://id.loc.gov/authorities/genreForms/gf2011026297">Geospatial data</mods:form>
      <mods:internetMediaType>application/octet-stream</mods:internetMediaType>
   </mods:physicalDescription>
   <mods:identifier type="ark">https://ark.colorado.edu/ark:47540/5c813b28cbb97a000bc586a7</mods:identifier>
   <mods:abstract>Shapefile Format –This data set contains the Oil Shale Leases for the State of Colorado, derived from Legal Land Descriptions (LLD) contained in the US Bureau of Land Management LR2000 Database, and geocoded (mapped) using the Public Land Survey System (PLSS) / Geographic Coordinate Data Base (GCBD) derived from the most accurate survey data available through BLM Cadastral Survey workforce.</mods:abstract>
   <mods:accessCondition type="use and reproduction">The organization that
      has made the Item available believes that the Item is in the Public Domain under the laws of
      the United States.</mods:accessCondition>
   <mods:location>
      <mods:url access="object in context">https://geo.colorado.edu/catalog/47540-5c813b28cbb97a000bc586a7</mods:url>
   </mods:location>
   <mods:relatedItem type="original">
   <mods:location>
      <mods:url access="object in context">https://www.blm.gov/site-page/services-geospatial-gis-data-colorado</mods:url>
   </mods:location>
   </mods:relatedItem>
   <mods:recordInfo>
      <mods:recordCreationDate encoding="w3cdtf">2019-05-23</mods:recordCreationDate>
      <mods:recordOrigin>Record created using source metadata with additional metadata provided by the University of Colorado Boulder Libraries.</mods:recordOrigin>
      <mods:recordContentSource>University of Colorado Boulder Libraries</mods:recordContentSource>
   </mods:recordInfo>
</mods:mods>