<?xml version='1.0' encoding='utf8'?>
<mods:mods xmlns:mods="http://www.loc.gov/mods/v3"
   xmlns:xsi="http://www.w3.org/2001/XMLSchema-instance"
   xsi:schemaLocation="http://www.loc.gov/mods/v3 http://www.loc.gov/standards/mods/v3/mods-3-7.xsd">
   <mods:titleInfo>
      <mods:title>United States Census Bureau, Colorado Counties</mods:title>
   </mods:titleInfo>
   <mods:typeOfResource>Dataset</mods:typeOfResource>
   <mods:originInfo>
      <mods:dateIssued encoding="w3cdtf">2019</mods:dateIssued>
      <mods:publisher>U.S. Department of Commerce, U.S. Census Bureau, Geography Division</mods:publisher>
   </mods:originInfo>
   <mods:language>
      <mods:languageTerm type="text">English</mods:languageTerm>
   </mods:language>
   <mods:subject valueURI="http://id.worldcat.org/fast/fst01411644">
      <mods:topic>Counties</mods:topic>
   </mods:subject>
   
   <mods:subject>
      <mods:geographic>Colorado</mods:geographic>
   </mods:subject>
   <mods:name type="corporate">
      <mods:namePart>U.S. Department of Commerce, U.S. Census Bureau, Geography Division</mods:namePart>
      <mods:role>
         <mods:roleTerm type="text">creator</mods:roleTerm>
      </mods:role>
   </mods:name>
   <mods:physicalDescription>
      <mods:form authority="LCGFT" authorityURI="http://id.loc.gov/authorities/genreForms/gf2011026721">Vector data</mods:form>
      <mods:internetMediaType>application/octet-stream</mods:internetMediaType>
   </mods:physicalDescription>
   <mods:identifier type="ark"></mods:identifier>
   <mods:abstract>The TIGER/Line shapefiles and related database files (.dbf) are an extract of selected geographic and cartographic information from the U.S. Census Bureau's Master Address File / Topologically Integrated Geographic Encoding and Referencing (MAF/TIGER) Database (MTDB). The MTDB represents a seamless national file with no overlaps or gaps between parts, however, each TIGER/Line shapefile is designed to stand alone as an independent data set, or they can be combined to cover the entire nation. The boundaries for counties and equivalent entities are as of January 1, 2019, primarily as reported through the Census Bureau's Boundary and Annexation Survey (BAS)."</mods:abstract>
   <mods:accessCondition type="use and reproduction"
      xmlns:xlink="https://rightsstatements.org/page/NoC-US/1.0/?language=en">The organization that
      has made the Item available believes that the Item is in the Public Domain under the laws of the
      United States.</mods:accessCondition>
   <mods:location>
      <mods:url access="object in context">https://geo.colorado.edu/catalog/47540-5e712aeda3d91e0009f59fc7</mods:url>
   </mods:location>
   <mods:relatedItem type="original">
      <mods:location>
         <mods:url access="object in context">https://www.census.gov/geographies/mapping-files.html</mods:url>
      </mods:location>
   </mods:relatedItem>
   <mods:recordInfo>
      <mods:recordCreationDate encoding="w3cdtf">2020-03-20</mods:recordCreationDate>
      <mods:recordOrigin>Record created using source metadata with additional metadata provided by the University of Colorado Boulder Libraries.</mods:recordOrigin>
      <mods:recordContentSource>University of Colorado Boulder Libraries</mods:recordContentSource>
   </mods:recordInfo>
</mods:mods>
